LICENSE
MANIFEST.in
README.rst
setup.py
django_hackref.egg-info/PKG-INFO
django_hackref.egg-info/SOURCES.txt
django_hackref.egg-info/dependency_links.txt
django_hackref.egg-info/requires.txt
django_hackref.egg-info/top_level.txt
hackref/__init__.py
hackref/admin.py
hackref/apps.py
hackref/models.py
hackref/tests.py
hackref/urls.py
hackref/utils.py
hackref/views.py
hackref/migrations/0001_initial.py
hackref/migrations/__init__.py
hackref/templates/hackref/snippets/referred_user_links.html