Metadata-Version: 1.1
Name: django-hackref
Version: 0.1.3
Summary: A Django app to create, monitor and track user referral links
Home-page: https://github.com/jmitchel3/django-hackref
Author: Justin Mitchel
Author-email: hello@teamcfe.com
License: MIT License
Keywords: django referrals growth marketing
Platform: UNKNOWN
Classifier: Environment :: Web Environment
Classifier: Framework :: Django
Classifier: Framework :: Django :: 1.9
Classifier: Intended Audience :: Developers
Classifier: License :: OSI Approved :: MIT License
Classifier: Operating System :: OS Independent
Classifier: Programming Language :: Python
Classifier: Programming Language :: Python :: 2
Classifier: Programming Language :: Python :: 2.7
Classifier: Programming Language :: Python :: 3
Classifier: Programming Language :: Python :: 3.4
Classifier: Programming Language :: Python :: 3.5
Classifier: Topic :: Internet :: WWW/HTTP
Classifier: Topic :: Internet :: WWW/HTTP :: Dynamic Content
